roboteq/__init__.py
roboteq/roboteq_constants.py
roboteq/roboteq_device.py
roboteq-0.8.dist-info/LICENCE
roboteq-0.8.dist-info/METADATA
roboteq-0.8.dist-info/WHEEL
roboteq-0.8.dist-info/top_level.txt
roboteq-0.8.dist-info/RECORD
