Metadata-Version: 2.1
Name: roboteq
Version: 0.8
Summary: Port of the roboteq API
Home-page: https://github.com/daltonpearson/roboteq
Author: Dalton Pearson
Author-email: daltonpearson1997@gmail.com
License: MIT
Platform: UNKNOWN
